vis_method/Hieu.py
vis_method/__init__.py
vis_method/delta.py
vis_method/feature_selection.py
vis_method/twins.py
vis_method/value.py
vis_method/yearAndLastYear.py
vis_method-2.9.2.dist-info/METADATA
vis_method-2.9.2.dist-info/WHEEL
vis_method-2.9.2.dist-info/top_level.txt
vis_method-2.9.2.dist-info/RECORD
